image_processing/src/bw_converter.sv
//now runs on 65 MHz:
module bw_converter (
  input wire clk_in,
  input wire [10:0] hcount_in,
  input wire [9:0] vcount_in,
  input wire data_valid_in,
  input wire [15:0] pixel_in,
  output logic pixel_out,
  output logic [10:0] hcount_out,
  output logic [9:0] vcount_out,
  output logic data_valid_out
  );

  logic [4:0] r;
  logic [5:0] g;
  logic [4:0] b;

  assign r = pixel_in[15:11];
  assign g = pixel_in[10:5];
  assign b = pixel_in[4:0];

  always_ff @(posedge clk_in) begin
    // if gray, set pixel black
    if (r <= 10 && g <= 10 && b <= 10)begin
        pixel_out <= 1;
    // if dark colors, set pixel black
    end else if ((r <= 5 && g <= 10) || (g <= 10 && b <= 5) || (b <= 5 && r <= 5)) begin
        pixel_out <= 1;
    end else begin
        pixel_out <= 0;
    end

    data_valid_out <= data_valid_in;
    hcount_out <= hcount_in;
    vcount_out <= vcount_in;

  end
endmodule

image_processing/sim/bw_converter_tb.sv
`timescale 1ns / 1ps
`default_nettype none

module bw_converter_tb;
  //make logics for inputs and outputs!


  logic clk_in;
  logic [10:0] hcount_in;
  logic [9:0] vcount_in;
  logic data_valid_in;
  logic [15:0] pixel_in;
  logic pixel_out;
  logic [10:0] hcount_out;
  logic [9:0] vcount_out;
  logic data_valid_out;

    bw_converter uut (
  .clk_in(clk_in),
  .hcount_in(hcount_in),
  .vcount_in(vcount_in),
  .data_valid_in(data_valid_in),
  .pixel_in(pixel_in),
  .pixel_out(pixel_out),
  .hcount_out(hcount_out),
  .vcount_out(vcount_out),
  .data_valid_out(data_valid_out)
  );

  always begin
    #5;
    clk_in = !clk_in;
  end


  //initial block...this is our test simulation
  initial begin
    $display("Starting Sim"); //print nice message
    $dumpfile("bw_converter.vcd"); //file to store value change dump (vcd)
    $dumpvars(0,bw_converter_tb); //store everything at the current level and below
    $display("Testing assorted values");
    clk_in = 0;

    data_valid_in = 0;
    hcount_in = 42;
    vcount_in = 69;
    #10;
    data_valid_in = 1;
    pixel_in = 16'b00000_000000_00000;
    #10;

    $display("pixel_out=%4d", pixel_out);

    data_valid_in = 0;
    hcount_in = 42;
    vcount_in = 69;
    #10;
    data_valid_in = 1;
    #10;
    pixel_in = 16'b11111_111111_11111;
    #10;

    $display("pixel_out=%4d", pixel_out);

    data_valid_in = 0;
    hcount_in = 42;
    vcount_in = 69;
    #10;
    data_valid_in = 1;
    #10;
    pixel_in = 16'b00000_111111_00000;
    #10;

    $display("pixel_out=%4d", pixel_out);

    
    $display("Finishing Sim"); //print nice message
    $finish;

  end
endmodule //bw_converter_tb

`default_nettype wire

image_processing/bw_converter.vcd
$date
	Fri Dec  9 01:03:44 2022
$end
$version
	Icarus Verilog
$end
$timescale
	1ps
$end
$scope module bw_converter_tb $end
$var wire 10 ! vcount_out [9:0] $end
$var wire 1 " pixel_out $end
$var wire 11 # hcount_out [10:0] $end
$var wire 1 $ data_valid_out $end
$var reg 1 % clk_in $end
$var reg 1 & data_valid_in $end
$var reg 11 ' hcount_in [10:0] $end
$var reg 16 ( pixel_in [15:0] $end
$var reg 10 ) vcount_in [9:0] $end
$scope module uut $end
$var wire 1 % clk_in $end
$var wire 1 & data_valid_in $end
$var wire 11 * hcount_in [10:0] $end
$var wire 16 + pixel_in [15:0] $end
$var wire 10 , vcount_in [9:0] $end
$var wire 5 - r [4:0] $end
$var wire 6 . g [5:0] $end
$var wire 5 / b [4:0] $end
$var reg 1 $ data_valid_out $end
$var reg 11 0 hcount_out [10:0] $end
$var reg 1 " pixel_out $end
$var reg 10 1 vcount_out [9:0] $end
$upscope $end
$upscope $end
$enddefinitions $end
#0
$dumpvars
bx 1
bx 0
bx /
bx .
bx -
b1000101 ,
bx +
b101010 *
b1000101 )
bx (
b101010 '
0&
0%
x$
bx #
x"
bx !
$end
#5000
b1000101 !
b1000101 1
b101010 #
b101010 0
0$
0"
1%
#10000
b0 -
b0 .
b0 /
0%
b0 (
b0 +
1&
#15000
1$
1"
1%
#20000
0%
0&
#25000
0$
1%
#30000
0%
1&
#35000
1$
1%
#40000
b11111 -
b111111 .
b11111 /
0%
b1111111111111111 (
b1111111111111111 +
#45000
0"
1%
#50000
0%
0&
#55000
0$
1%
#60000
0%
1&
#65000
1$
1%
#70000
b0 -
b0 /
0%
b11111100000 (
b11111100000 +
#75000
1"
1%
