networking/transmitting/src/bitorder.sv
`default_nettype none
`timescale 1ns / 1ps

module bitorder (
    input wire clk,
    input wire rst,
    input wire axiiv,
    input wire [1:0] axiid,

    output logic axiov,
    output logic [1:0] axiod
);
    logic [7:0] buf_a, buf_b;
    logic read_buf;
    logic [1:0] buf_counter;

    localparam IDLE = 0;
    localparam RNOW = 1; // Read, no write (start of sequence)
    localparam RANDW = 2; // Read and write (middle of sequence)
    localparam WNOR = 3; // Write, no read (end of sequence)
    logic [1:0] state;

    always_ff @(posedge clk) begin
        if (rst) begin
            read_buf <= 1'b0;
            buf_counter <= 0;
            buf_a <= 8'b0;
            buf_b <= 8'b0;
            axiov <= 1'b0;
            state <= IDLE;
        end
        case (state)
            IDLE: begin
                axiod <= 2'b0;
                axiov <= 1'b0;
                if (axiiv == 1'b1) begin
                    buf_b <= 8'b0;
                    buf_a <= {axiid, 6'b0};
                    read_buf <= 1'b0;
                    buf_counter <= 0;
                    state <= RNOW;
                end
            end
            RNOW: begin
                if (axiiv == 1'b1) begin
                    if (buf_counter == 3) begin // go-to RANDW
                        buf_b <= {axiid, buf_b[7:2]};
                        axiod <= buf_a[7:6]; // output is from buf_a
                        axiov <= 1'b1; // write buffer is buf_a
                        read_buf <= ~read_buf;
                        buf_counter <= 0;
                        state <= RANDW;
                    end else begin
                        buf_a <= {axiid, buf_a[7:2]};
                        buf_counter <= buf_counter + 1;
                    end
                end else begin // valid went low
                    if (buf_counter == 3) begin // go-to WNOR
                        axiod <= buf_a[7:6]; // output is from buf_a
                        axiov <= 1'b1; // write buffer is buf_a
                        read_buf <= 1'b1;
                        buf_counter <= 0;
                        state <= WNOR;
                    end else begin
                        buf_counter <= 0;
                        buf_a <= 8'b0;
                        state <= IDLE;
                    end
                end
            end
            RANDW: begin
                axiov <= 1'b1;
                if (axiiv == 1'b1) begin
                    if (read_buf == 1'b0) begin
                        case (buf_counter)
                            3: begin
                                buf_b <= {axiid, buf_b[7:2]};
                                axiod <= buf_a[7:6];
                            end
                            0: begin
                                buf_a <= {axiid, buf_a[7:2]};
                                axiod <= buf_b[5:4];
                            end
                            1: begin
                                buf_a <= {axiid, buf_a[7:2]};
                                axiod <= buf_b[3:2];
                            end
                            2: begin
                                buf_a <= {axiid, buf_a[7:2]};
                                axiod <= buf_b[1:0];
                            end
                        endcase
                    end else begin
                        case (buf_counter)
                            3: begin 
                                buf_a <= {axiid, buf_a[7:2]};
                                axiod <= buf_b[7:6];
                            end
                            0: begin
                                buf_b <= {axiid, buf_b[7:2]};
                                axiod <= buf_a[5:4];
                            end
                            1: begin
                                buf_b <= {axiid, buf_b[7:2]};
                                axiod <= buf_a[3:2];
                            end
                            2: begin
                                buf_b <= {axiid, buf_b[7:2]};
                                axiod <= buf_a[1:0];
                            end
                        endcase
                    end
                    if (buf_counter == 3) begin
                        read_buf <= ~read_buf;
                        buf_counter <= 0;
                    end else begin
                        buf_counter <= buf_counter + 1;
                    end
                end else begin // handle invalid i.e. transition to WNOR
                    if (read_buf == 1'b0) begin
                        case (buf_counter)
                            3: begin
                                axiod <= buf_a[7:6];
                            end
                            0: begin
                                axiod <= buf_b[5:4];
                            end
                            1: begin
                                axiod <= buf_b[3:2];
                            end
                            2: begin
                                axiod <= buf_b[1:0];
                            end
                        endcase
                    end else begin
                        case (buf_counter)
                            3: begin
                                axiod <= buf_b[7:6];
                            end
                            0: begin
                                axiod <= buf_a[5:4];
                            end
                            1: begin
                                axiod <= buf_a[3:2];
                            end
                            2: begin
                                axiod <= buf_a[1:0];
                            end
                        endcase
                    end
                    axiov <= 1'b1;
                    if (buf_counter == 3) begin
                        buf_counter <= 0;
                        read_buf <= ~read_buf;
                        state <= WNOR;
                    end else begin
                        buf_counter <= buf_counter + 1;
                        state <= WNOR;
                    end
                end
            end
            WNOR: begin
                axiov <= 1'b1;
                // if (axiiv == 1'b0) begin
                    if (read_buf == 1'b0) begin
                        case (buf_counter)
                            3: begin 
                                axiod <= buf_b[7:6];
                            end
                            0: begin 
                                axiod <= buf_b[5:4];
                            end
                            1: begin 
                                axiod <= buf_b[3:2];
                            end
                            2: begin 
                                axiod <= buf_b[1:0];
                            end
                        endcase
                    end else begin
                        case (buf_counter)
                            3: begin 
                                axiod <= buf_a[7:6];
                            end
                            0: begin 
                                axiod <= buf_a[5:4];
                            end
                            1: begin 
                                axiod <= buf_a[3:2];
                            end
                            2: begin 
                                axiod <= buf_a[1:0];
                            end
                        endcase
                    end
                    if (buf_counter == 3) begin
                        axiov <= 1'b0;
                        axiod <= 2'b00;
                        buf_counter <= 0;
                        state <= IDLE;
                    end else buf_counter <= buf_counter + 1; 
                // end else begin // handle new sequence i.e. transition to RNOW

                // end
            end
        endcase
    end


endmodule

`default_nettype wire

networking/receiving/sim/bitorder_tb.sv
`default_nettype none
`timescale 1ns / 1ps

module bitorder_tb();
    logic clk_in; // System clock
    logic rst_in; // System reset
    logic axiiv; // Data valid input
    logic [1:0] axiid; // Data input bus

    logic axiov; // Output valid
    logic [1:0] axiod; // Output data bus

    bitorder uut (
        .clk(clk_in),
        .rst(rst_in),
        .axiiv(axiiv), 
        .axiid(axiid),
        .axiov(axiov),
        .axiod(axiod)
        );

    always begin
        #10;
        clk_in = !clk_in;
    end

    initial begin
        $dumpfile("bitorder.vcd");
        $dumpvars(0, bitorder_tb);
        $display("Starting Sim");
        clk_in = 0;
        #10;
        rst_in = 0; 
        // use #20 for clock cycle 
        #20;
        rst_in = 1;
        #20; 
        rst_in = 0;
        $display("1: Only four bits of data");
        #100;
        axiiv = 1'b1;
        for (int i = 0; i<2; i = i + 1) begin 
            axiid = 2'b10;
            #20;
        end
        axiiv = 1'b0;
        axiid = 2'b0;
        #20;
        #100;
        $display("2: Exactly one byte of data");
        #100;
        axiiv = 1'b1;
        for (int i = 0; i<2; i = i + 1) begin 
            axiid = 2'b10;
            #20;
        end
        for (int i = 0; i<2; i = i + 1) begin
            axiid = 2'b11;
            #20;
        end
        axiiv = 1'b0;
        axiid = 2'b0;
        #20;
        #100;
        $display("3: 1.5 bytes, should only see 1 output");
        #100;
        axiiv = 1'b1;
        for (int i = 0; i<2; i = i + 1) begin 
            axiid = 2'b10;
            #20;
        end
        for (int i = 0; i<2; i = i + 1) begin
            axiid = 2'b11;
            #20;
        end
        for (int i = 0; i<2; i = i + 1) begin
            axiid = 2'b01;
            #20;
        end
        axiiv = 1'b0;
        axiid = 2'b0;
        #20;
        #100;
        $display("4: Two bytes of input, two bytes of output");
        #100;
        axiiv = 1'b1;
        for (int i = 0; i<2; i = i + 1) begin 
            axiid = 2'b10;
            #20;
        end
        for (int i = 0; i<2; i = i + 1) begin
            axiid = 2'b11;
            #20;
        end
        for (int i = 0; i<2; i = i + 1) begin
            axiid = 2'b01;
            #20;
        end
        for (int i = 0; i<2; i = i + 1) begin
            axiid = 2'b11;
            #20;
        end
        axiiv = 1'b0;
        axiid = 2'b0;
        #20;
        #100;
        $display("5: One more bit than two bytes");
        #100;
        axiiv = 1'b1;
        axiid = 2'b00;
        #20;
        axiid = 2'b01;
        #20;
        axiid = 2'b10;
        #20;
        axiid = 2'b11;
        #20;
        axiid = 2'b11;
        #20;
        axiid = 2'b10;
        #20;
        axiid = 2'b01;
        #20;
        axiid = 2'b10;
        #20;
        // axiiv = 1'b0;
        // axiid = 2'b00;
        // #20;
        // axiiv = 1'b0;
        // axiid = 2'b00;
        // #20;
        // axiiv = 1'b0;
        // axiid = 2'b00;
        // #20;
        // axiiv = 1'b1;
        axiid = 2'b01;
        #20;
        axiiv = 1'b0;
        axiid = 2'b0;
        #20;
        #100;
        $display("6: three bytes in, three bytes out");
        // unimplemented, passes in lab05 testbench
        $display("7: two bytes in a row sans reset");
        // unimplemented, passes in lab05 testbench
        $display("8: three bytes + change sans reset");
        // unimplemented, passes in lab05 testbench
        $display("9: so many bytes");
        // unimplemented, passes in lab05 testbench
        $display("10: symmetric resest logic");
        // unimplemented, passes in lab05 testbench
        $display("Finishing Sim"); //print nice message
        $finish;

    end
endmodule // bitorder_tb

`default_nettype wire

networking/obj/bitorder.vcd
$date
	Mon Dec  5 14:44:38 2022
$end
$version
	Icarus Verilog
$end
$timescale
	1ps
$end
$scope module bitorder_tb $end
$var wire 1 ! axiov $end
$var wire 2 " axiod [1:0] $end
$var reg 2 # axiid [1:0] $end
$var reg 1 $ axiiv $end
$var reg 1 % clk_in $end
$var reg 1 & rst_in $end
$scope module uut $end
$var wire 2 ' axiid [1:0] $end
$var wire 1 $ axiiv $end
$var wire 1 % clk $end
$var wire 1 & rst $end
$var reg 2 ( axiod [1:0] $end
$var reg 1 ! axiov $end
$var reg 8 ) buf_a [7:0] $end
$var reg 8 * buf_b [7:0] $end
$var reg 2 + buf_counter [1:0] $end
$var reg 1 , read_buf $end
$var reg 2 - state [1:0] $end
$upscope $end
$scope begin $ivl_for_loop0 $end
$var integer 32 . i [31:0] $end
$upscope $end
$scope begin $ivl_for_loop1 $end
$var integer 32 / i [31:0] $end
$upscope $end
$scope begin $ivl_for_loop2 $end
$var integer 32 0 i [31:0] $end
$upscope $end
$scope begin $ivl_for_loop3 $end
$var integer 32 1 i [31:0] $end
$upscope $end
$scope begin $ivl_for_loop4 $end
$var integer 32 2 i [31:0] $end
$upscope $end
$scope begin $ivl_for_loop5 $end
$var integer 32 3 i [31:0] $end
$upscope $end
$scope begin $ivl_for_loop6 $end
$var integer 32 4 i [31:0] $end
$upscope $end
$scope begin $ivl_for_loop7 $end
$var integer 32 5 i [31:0] $end
$upscope $end
$scope begin $ivl_for_loop8 $end
$var integer 32 6 i [31:0] $end
$upscope $end
$scope begin $ivl_for_loop9 $end
$var integer 32 7 i [31:0] $end
$upscope $end
$upscope $end
$enddefinitions $end
#0
$dumpvars
b0 7
b0 6
b0 5
b0 4
b0 3
b0 2
b0 1
b0 0
b0 /
b0 .
bx -
x,
bx +
bx *
bx )
bx (
bx '
x&
0%
x$
bx #
bx "
x!
$end
#10000
0&
1%
#20000
0%
#30000
b0 -
0!
b0 *
b0 )
b0 +
0,
1%
1&
#40000
0%
#50000
b0 "
b0 (
1%
0&
#60000
0%
#70000
1%
#80000
0%
#90000
1%
#100000
0%
#110000
1%
#120000
0%
#130000
1%
#140000
0%
#150000
b1 -
b10000000 )
1%
b10 #
b10 '
1$
#160000
0%
#170000
b1 +
b10100000 )
1%
b1 .
#180000
0%
#190000
b0 -
b0 )
b0 +
1%
b0 #
b0 '
0$
b10 .
#200000
0%
#210000
1%
#220000
0%
#230000
1%
#240000
0%
#250000
1%
#260000
0%
#270000
1%
#280000
0%
#290000
1%
#300000
0%
#310000
1%
#320000
0%
#330000
1%
#340000
0%
#350000
1%
#360000
0%
#370000
1%
#380000
0%
#390000
1%
#400000
0%
#410000
b1 -
b10000000 )
1%
b10 #
b10 '
1$
#420000
0%
#430000
b1 +
b10100000 )
1%
b1 /
#440000
0%
#450000
b10 +
b11101000 )
1%
b11 #
b11 '
b10 /
#460000
0%
#470000
b11 +
b11111010 )
1%
b1 0
#480000
0%
#490000
b11 -
b0 +
1,
1!
b11 "
b11 (
1%
b0 #
b0 '
0$
b10 0
#500000
0%
#510000
b1 +
1%
#520000
0%
#530000
b10 +
b10 "
b10 (
1%
#540000
0%
#550000
b11 +
1%
#560000
0%
#570000
b0 -
b0 +
0!
b0 "
b0 (
1%
#580000
0%
#590000
1%
#600000
0%
#610000
1%
#620000
0%
#630000
1%
#640000
0%
#650000
1%
#660000
0%
#670000
1%
#680000
0%
#690000
1%
#700000
0%
#710000
b1 -
0,
b10000000 )
1%
b10 #
b10 '
1$
#720000
0%
#730000
b1 +
b10100000 )
1%
b1 1
#740000
0%
#750000
b10 +
b11101000 )
1%
b11 #
b11 '
b10 1
#760000
0%
#770000
b11 +
b11111010 )
1%
b1 2
#780000
0%
#790000
b10 -
b0 +
1,
1!
b11 "
b11 (
b1000000 *
1%
b1 #
b1 '
b10 2
#800000
0%
#810000
b1 +
b1010000 *
1%
b1 3
#820000
0%
#830000
b11 -
b10 +
b10 "
b10 (
1%
b0 #
b0 '
0$
b10 3
#840000
0%
#850000
b11 +
1%
#860000
0%
#870000
b0 -
b0 +
0!
b0 "
b0 (
1%
#880000
0%
#890000
1%
#900000
0%
#910000
1%
#920000
0%
#930000
1%
#940000
0%
#950000
1%
#960000
0%
#970000
1%
#980000
0%
#990000
1%
#1000000
0%
#1010000
1%
#1020000
0%
#1030000
1%
#1040000
0%
#1050000
b1 -
0,
b10000000 )
b0 *
1%
b10 #
b10 '
1$
#1060000
0%
#1070000
b1 +
b10100000 )
1%
b1 4
#1080000
0%
#1090000
b10 +
b11101000 )
1%
b11 #
b11 '
b10 4
#1100000
0%
#1110000
b11 +
b11111010 )
1%
b1 5
#1120000
0%
#1130000
b10 -
b0 +
1,
1!
b11 "
b11 (
b1000000 *
1%
b1 #
b1 '
b10 5
#1140000
0%
#1150000
b1 +
b1010000 *
1%
b1 6
#1160000
0%
#1170000
b10 +
b10 "
b10 (
b11010100 *
1%
b11 #
b11 '
b10 6
#1180000
0%
#1190000
b11 +
b11110101 *
1%
b1 7
#1200000
0%
#1210000
b11 -
0,
b0 +
b11 "
b11 (
1%
b0 #
b0 '
0$
b10 7
#1220000
0%
#1230000
b1 +
1%
#1240000
0%
#1250000
b10 +
b1 "
b1 (
1%
#1260000
0%
#1270000
b11 +
1%
#1280000
0%
#1290000
b0 -
b0 +
0!
b0 "
b0 (
1%
#1300000
0%
#1310000
1%
#1320000
0%
#1330000
1%
#1340000
0%
#1350000
1%
#1360000
0%
#1370000
1%
#1380000
0%
#1390000
1%
#1400000
0%
#1410000
1%
#1420000
0%
#1430000
b1 -
b0 )
b0 *
1%
1$
#1440000
0%
#1450000
b1 +
b1000000 )
1%
b1 #
b1 '
#1460000
0%
#1470000
b10 +
b10010000 )
1%
b10 #
b10 '
#1480000
0%
#1490000
b11 +
b11100100 )
1%
b11 #
b11 '
#1500000
0%
#1510000
b10 -
b0 +
1,
1!
b11 "
b11 (
b11000000 *
1%
#1520000
0%
#1530000
b1 +
b10 "
b10 (
b10110000 *
1%
b10 #
b10 '
#1540000
0%
#1550000
b10 +
b1 "
b1 (
b1101100 *
1%
b1 #
b1 '
#1560000
0%
#1570000
b11 +
b0 "
b0 (
b10011011 *
1%
b10 #
b10 '
#1580000
0%
#1590000
b0 +
0,
b10 "
b10 (
b1111001 )
1%
b1 #
b1 '
#1600000
0%
#1610000
b11 -
b1 +
b1 "
b1 (
1%
b0 #
b0 '
0$
#1620000
0%
#1630000
b10 +
b10 "
b10 (
1%
#1640000
0%
#1650000
b11 +
b11 "
b11 (
1%
#1660000
0%
#1670000
b0 -
b0 +
0!
b0 "
b0 (
1%
