integration/receiving/src/firewall.sv
`default_nettype none
`timescale 1ns / 1ps

module firewall (
    input wire clk,
    input wire rst,
    input wire axiiv,
    input wire [1:0] axiid,

    output logic axiov,
    output logic [1:0] axiod
);
     // Device Address 69:69:5A:06:54:91
    logic [47:0] device_addr = 48'b01101001_01101001_01011010_00000110_01010100_10010001;
    logic [47:0] broadcast_addr = 48'b11111111_11111111_11111111_11111111_11111111_11111111;
    logic [47:0] read_addr;
    logic [5:0] counter;

    localparam IDLE = 0;
    localparam READ = 1; // read address, determine once full
    localparam HEADERWAIT = 2; // address matches, wait to finish header
    localparam FORWARD = 3; // forwarding data
    localparam IGNORE = 4;
    logic [2:0] state;

    always_ff @(posedge clk) begin
        if (rst) begin
            read_addr <= 48'b0;
            counter <= 0;
            state <= IDLE;
        end
        case (state)
            IDLE: begin
                if (axiiv == 1'b1) begin
                    read_addr <= {46'b0, axiid};
                    counter <= 0;
                    state <= READ;
                end
            end
            READ: begin
                if (axiiv == 1'b1) begin
                    if (counter == 23) begin
                        if (read_addr == device_addr || read_addr == broadcast_addr) begin
                            counter <= counter + 1;
                            state <= HEADERWAIT;
                        end else begin
                            state <= IGNORE;
                        end
                    end else begin
                        read_addr <= {read_addr[45:0], axiid};
                        counter <= counter + 1;
                    end
                end else begin
                    counter <= 0;
                    state <= IDLE;
                end
            end
            HEADERWAIT: begin
                if (axiiv == 1'b1) begin
                    if (counter == 55) begin
                        state <= FORWARD;
                    end else begin
                        counter <= counter + 1;
                    end
                end else begin
                    counter <= 0;
                    state <= IDLE;
                end
            end
            FORWARD: begin
                if (axiiv == 1'b0) begin 
                    state <= IDLE;
                    read_addr <= 48'b0;
                    counter <= 0;
                end
            end
            IGNORE: begin
                if (axiiv == 1'b0) begin
                    state <= IDLE;
                    read_addr <= 48'b0;
                    counter <= 0;
                end
            end
        endcase
    end

    always_comb begin
        if (rst == 1'b1) begin 
            axiod = 2'b00;
            axiov = 1'b0;
        end else begin
            axiod = ((read_addr == device_addr || read_addr == broadcast_addr) && counter == 55) ? axiid : 2'b00; 
            axiov = ((read_addr == device_addr || read_addr == broadcast_addr) && counter == 55) ? axiiv : 1'b0; 
        end
    end

endmodule

`default_nettype wire

networking/receiving/sim/firewall_tb.sv
`default_nettype none
`timescale 1ns / 1ps

module firewall_tb();
    logic clk_in; // System clock
    logic rst_in; // System reset
    logic axiiv; // Data valid input
    logic [1:0] axiid; // Data input bus

    logic axiov; // Output valid
    logic [1:0] axiod; // Output data bus

    firewall uut (
        .clk(clk_in),
        .rst(rst_in),
        .axiiv(axiiv), 
        .axiid(axiid),
        .axiov(axiov),
        .axiod(axiod)
        );

    always begin
        #10;
        clk_in = !clk_in;
    end

    initial begin
        $dumpfile("firewall.vcd");
        $dumpvars(0, firewall_tb);
        $display("Starting Sim");
        clk_in = 0;
        // #10;
        rst_in = 0; 
        // use #20 for clock cycle 
        #20;
        rst_in = 1;
        #20; 
        rst_in = 0;
        $display("1: Garbage MAC Address");
        #100;
        axiiv = 1'b1;
        for (int i = 0; i<24; i = i + 1) begin 
            axiid = 2'b10;
            #20;
        end
        axiiv = 1'b0;
        axiid = 2'b0;
        #20;
        #500;
        $display("2: Off by one MAC Address");
        // device_addr = 01101001_01101001_01011010_00000110_01010100_10010001 
        #100; 
        axiiv = 1'b1;
        axiid = 2'b01; // 69
        #20;
        axiid = 2'b10;
        #20;
        axiid = 2'b10;
        #20;
        axiid = 2'b01;
        #20;
        axiid = 2'b01; // 69
        #20;
        axiid = 2'b10;
        #20;
        axiid = 2'b10;
        #20;
        axiid = 2'b01;
        #20;
        axiid = 2'b01; // 5A
        #20;
        axiid = 2'b01;
        #20;
        axiid = 2'b10;
        #20;
        axiid = 2'b10;
        #20;
        axiid = 2'b00; // 06
        #20;
        axiid = 2'b00;
        #20;
        axiid = 2'b01;
        #20;
        axiid = 2'b10;
        #20;
        axiid = 2'b01; // 54
        #20;
        axiid = 2'b01;
        #20;
        axiid = 2'b01;
        #20;
        axiid = 2'b00;
        #20;
        axiid = 2'b10; // 90 instead of 91
        #20;
        axiid = 2'b01;
        #20;
        axiid = 2'b00;
        #20;
        axiid = 2'b00;
        #20;
        for (int i = 0; i<4; i = i + 1) begin // 2 bytes of arbitrary data
            axiid = 2'b10;
            #20;
        end
        axiiv = 1'b0;
        axiid = 2'b0;
        #20;
        #100;
        $display("3: Broadcast Address");
        #100;
        axiiv = 1'b1;
        // Destination Address
        for (int i = 0; i<24; i = i + 1) begin 
            axiid = 2'b11;
            #20;
        end
        // Header Address
        for (int i = 0; i<24; i = i + 1) begin 
            axiid = 2'b01;
            #20;
        end
        // Data length
        for (int i = 0; i<7; i = i + 1) begin
            axiid = 2'b00;
            #20;
        end
        axiid = 2'b10;
        #20;
        // Arbitrary data
        // for (int i = 0; i<4; i = i + 1) begin 
        //     axiid = 2'b01;
        //     #20;
        // end
        axiid = 2'b11;
        #20;
        axiid = 2'b00;
        #20;
        axiid = 2'b01;
        #20;
        axiid = 2'b11;
        #20;
        axiiv = 1'b0;
        axiid = 2'b0;
        #20;
        #100;
        $display("4: Personalized MAC Address");
        $display("5: Personal mac + tiny message");
        $display("6: Personal mac + beeg message");
        // unimplemented
        $display("Finishing Sim"); //print nice message
        $finish;

    end
endmodule // firewall_tb

`default_nettype wire

networking/obj/firewall.vcd
$date
	Tue Dec  6 14:39:17 2022
$end
$version
	Icarus Verilog
$end
$timescale
	1ps
$end
$scope module firewall_tb $end
$var wire 1 ! axiov $end
$var wire 2 " axiod [1:0] $end
$var reg 2 # axiid [1:0] $end
$var reg 1 $ axiiv $end
$var reg 1 % clk_in $end
$var reg 1 & rst_in $end
$scope module uut $end
$var wire 2 ' axiid [1:0] $end
$var wire 1 $ axiiv $end
$var wire 1 % clk $end
$var wire 1 & rst $end
$var reg 2 ( axiod [1:0] $end
$var reg 1 ! axiov $end
$var reg 48 ) broadcast_addr [47:0] $end
$var reg 6 * counter [5:0] $end
$var reg 48 + device_addr [47:0] $end
$var reg 48 , read_addr [47:0] $end
$var reg 3 - state [2:0] $end
$upscope $end
$scope begin $ivl_for_loop0 $end
$var integer 32 . i [31:0] $end
$upscope $end
$scope begin $ivl_for_loop1 $end
$var integer 32 / i [31:0] $end
$upscope $end
$scope begin $ivl_for_loop2 $end
$var integer 32 0 i [31:0] $end
$upscope $end
$scope begin $ivl_for_loop3 $end
$var integer 32 1 i [31:0] $end
$upscope $end
$scope begin $ivl_for_loop4 $end
$var integer 32 2 i [31:0] $end
$upscope $end
$upscope $end
$enddefinitions $end
#0
$dumpvars
b0 2
b0 1
b0 0
b0 /
b0 .
bx -
bx ,
b11010010110100101011010000001100101010010010001 +
bx *
b111111111111111111111111111111111111111111111111 )
bx (
bx '
0&
0%
x$
bx #
bx "
x!
$end
#10000
1%
#20000
0!
b0 "
b0 (
0%
1&
#30000
b0 -
b0 *
b0 ,
1%
#40000
0%
0&
#50000
1%
#60000
0%
#70000
1%
#80000
0%
#90000
1%
#100000
0%
#110000
1%
#120000
0%
#130000
1%
#140000
0%
b10 #
b10 '
1$
#150000
b1 -
b10 ,
1%
#160000
0%
b1 .
#170000
b1 *
b1010 ,
1%
#180000
0%
b10 .
#190000
b10 *
b101010 ,
1%
#200000
0%
b11 .
#210000
b11 *
b10101010 ,
1%
#220000
0%
b100 .
#230000
b100 *
b1010101010 ,
1%
#240000
0%
b101 .
#250000
b101 *
b101010101010 ,
1%
#260000
0%
b110 .
#270000
b110 *
b10101010101010 ,
1%
#280000
0%
b111 .
#290000
b111 *
b1010101010101010 ,
1%
#300000
0%
b1000 .
#310000
b1000 *
b101010101010101010 ,
1%
#320000
0%
b1001 .
#330000
b1001 *
b10101010101010101010 ,
1%
#340000
0%
b1010 .
#350000
b1010 *
b1010101010101010101010 ,
1%
#360000
0%
b1011 .
#370000
b1011 *
b101010101010101010101010 ,
1%
#380000
0%
b1100 .
#390000
b1100 *
b10101010101010101010101010 ,
1%
#400000
0%
b1101 .
#410000
b1101 *
b1010101010101010101010101010 ,
1%
#420000
0%
b1110 .
#430000
b1110 *
b101010101010101010101010101010 ,
1%
#440000
0%
b1111 .
#450000
b1111 *
b10101010101010101010101010101010 ,
1%
#460000
0%
b10000 .
#470000
b10000 *
b1010101010101010101010101010101010 ,
1%
#480000
0%
b10001 .
#490000
b10001 *
b101010101010101010101010101010101010 ,
1%
#500000
0%
b10010 .
#510000
b10010 *
b10101010101010101010101010101010101010 ,
1%
#520000
0%
b10011 .
#530000
b10011 *
b1010101010101010101010101010101010101010 ,
1%
#540000
0%
b10100 .
#550000
b10100 *
b101010101010101010101010101010101010101010 ,
1%
#560000
0%
b10101 .
#570000
b10101 *
b10101010101010101010101010101010101010101010 ,
1%
#580000
0%
b10110 .
#590000
b10110 *
b1010101010101010101010101010101010101010101010 ,
1%
#600000
0%
b10111 .
#610000
b10111 *
b101010101010101010101010101010101010101010101010 ,
1%
#620000
0%
b0 #
b0 '
0$
b11000 .
#630000
b0 -
b0 *
1%
