networking/src/identity.sv
`default_nettype none
`timescale 1ns / 1ps

module identity (
    input wire clk, // 50 MHz clock
    input wire rst, // System reset
    input wire axiiv, // Data valid input
    input wire [1:0] axiid, // Data input bus

    output logic axiov, // Output valid
    output logic [1:0] axiod // Output data bus
);
    // Device Address 69:69:5A:06:54:90
    logic [47:0] source_addr = 48'b01101001_01101001_01011010_00000110_01010100_10010000;
    // Destination Address 69:69:5A:06:54:91
    logic [47:0] destination_addr = 48'b01101001_01101001_01011010_00000110_01010100_10010001;
    // Broadcast Address
    // logic [47:0] destination_addr = 48'b11111111_11111111_11111111_11111111_11111111_11111111; 
    logic [15:0] ethertype = 16'b0000001_00000001;

    localparam IDLE = 0;
    localparam HEADER = 1; // Header (Destination, Source, and Length)
    localparam READTRANSMIT = 2; // Data input valid and transmitting
    localparam TRANSMIT = 3; // Data input no longer valid and transmitting
    logic [1:0] state;

    logic [111:0] data_buf; // data stored while start of frame sent
    logic reading_data; // check signal to avoid errant data after going low
    int data_counter; // Need to count to 111 (112 bits)
    logic [5:0] cycle_counter; // Need to count to 56 (cycles)

    always_ff @(posedge clk) begin
        if (rst == 1'b1) begin
            axiov <= 1'b0;
            axiod <= 2'b0;
            data_counter <= 0;
            cycle_counter <= 6'b0;
            state <= IDLE;
        end
        case (state)
            IDLE: begin
                if (axiiv == 1'b1) begin
                    axiov <= 1'b1;
                    data_buf <= {110'b0, axiid};
                    reading_data <= 1'b1;
                    data_counter <= 1;

                    axiod <= destination_addr[47:46];
                    destination_addr <= {destination_addr[45:0], destination_addr[47:46]};
                    cycle_counter <= 0;

                    state <= HEADER;
                end
            end
            HEADER: begin
                cycle_counter <= cycle_counter + 1;
                if (cycle_counter < 23) begin // Send destination address
                    axiod <= destination_addr[47:46];
                    destination_addr <= {destination_addr[45:0], destination_addr[47:46]};
                end else if (cycle_counter >= 23 && cycle_counter < 47) begin // Send source address
                    axiod <= source_addr[47:46];
                    source_addr <= {source_addr[45:0], source_addr[47:46]};
                end else if (cycle_counter >= 47 && cycle_counter < 55) begin // Send ethertype
                    axiod <= ethertype[15:14];
                    ethertype <= {ethertype[13:0], ethertype[15:14]};
                end else begin // Send first data 
                    if (axiiv == 1'b1 && reading_data == 1'b1) begin // still reading
                        axiod <= data_buf[111:110];
                        data_buf <= {data_buf[109:0], axiid};
                        state <= READTRANSMIT;
                    end else begin // no longer reading i.e. static
                        reading_data <= 1'b0;
                        axiod <= {data_buf[data_counter], data_buf[data_counter-1]};
                        data_counter <= data_counter - 2;
                        state <= TRANSMIT;
                    end
                end
                if (cycle_counter < 55) begin 
                    if (axiiv == 1'b1 && reading_data == 1'b1) begin
                        data_buf <= {data_buf[109:0], axiid};
                        data_counter <= data_counter + 2;
                    end else begin
                        reading_data <= 1'b0;
                    end
                end
            end
            READTRANSMIT: begin
                if (axiiv == 1'b1 && reading_data == 1'b1) begin
                    axiod <= data_buf[111:110];
                    data_buf <= {data_buf[109:0], axiid};
                end else begin
                    reading_data <= 1'b0;
                    axiod <= {data_buf[data_counter], data_buf[data_counter-1]};
                    data_counter <= data_counter - 2;
                    state <= TRANSMIT;
                end
            end
            TRANSMIT: begin
                if (data_counter > 0) begin
                    axiod <= {data_buf[data_counter], data_buf[data_counter-1]};
                    data_counter <= data_counter - 2;
                end else begin
                    axiov <= 1'b0;
                    data_counter <= 0;
                    cycle_counter <= 0;
                    state <= IDLE;
                end
            end
        endcase
    end
endmodule

`default_nettype wire

networking/transmitting/sim/identity_tb.sv
`default_nettype none
`timescale 1ns / 1ps

module identity_tb();
    logic clk_in; // System clock
    logic rst_in; // System reset
    logic axiiv; // Data valid input
    logic [1:0] axiid; // Data input bus

    logic axiov; // Output valid
    logic [1:0] axiod; // Output data bus

    identity uut (
        .clk(clk_in),
        .rst(rst_in),
        .axiiv(axiiv), 
        .axiid(axiid),
        .axiov(axiov),
        .axiod(axiod)
        );

    always begin
        #10;
        clk_in = !clk_in;
    end

    initial begin
        $dumpfile("identity.vcd");
        $dumpvars(0, identity_tb);
        $display("Starting Sim");
        clk_in = 0;
        #10;
        rst_in = 0; 
        // use #20 for clock cycle 
        #20;
        rst_in = 1;
        #20; 
        rst_in = 0;
        $display("1: Half a byte of data");
        #100;
        axiiv = 1'b1;
        axiid = 2'b10;
        #20;
        axiid = 2'b01;
        #20;
        axiiv = 1'b0;
        axiid = 2'b0;
        #20;
        #2000;
        $display("2: One byte of data");
        #100; 
        axiiv = 1'b1;
        axiid = 2'b01;
        #20
        axiid = 2'b10;
        #20;
        axiid = 2'b10;
        #20;
        axiid = 2'b01;
        #20;
        axiiv = 1'b0;
        axiid = 2'b0;
        #20;
        #2000;
        $display("3: 2 bytes of data");
        #100;
        axiiv = 1'b1;
        for (int i = 0; i<8; i = i + 1) begin 
            axiid = 2'b01;
            #20;
        end
        axiiv = 1'b0;
        axiid = 2'b0;
        #20;
        #2000;
        $display("4: 22 bytes of data");
        #100;
        axiiv = 1'b1;
        for (int i = 0; i<88; i = i + 1) begin 
            axiid = 2'b01;
            #20;
        end
        axiiv = 1'b0;
        axiid = 2'b00;
        #20;
        #2000;
        $display("Finishing Sim"); //print nice message
        $finish;

    end
endmodule // identity_tb

`default_nettype wire

networking/obj/identity.vcd
$date
	Thu Dec  8 18:07:20 2022
$end
$version
	Icarus Verilog
$end
$timescale
	1ps
$end
$scope module identity_tb $end
$var wire 1 ! axiov $end
$var wire 2 " axiod [1:0] $end
$var reg 2 # axiid [1:0] $end
$var reg 1 $ axiiv $end
$var reg 1 % clk_in $end
$var reg 1 & rst_in $end
$scope module uut $end
$var wire 2 ' axiid [1:0] $end
$var wire 1 $ axiiv $end
$var wire 1 % clk $end
$var wire 1 & rst $end
$var reg 2 ( axiod [1:0] $end
$var reg 1 ! axiov $end
$var reg 6 ) cycle_counter [5:0] $end
$var reg 112 * data_buf [111:0] $end
$var reg 48 + destination_addr [47:0] $end
$var reg 16 , ethertype [15:0] $end
$var reg 1 - reading_data $end
$var reg 48 . source_addr [47:0] $end
$var reg 2 / state [1:0] $end
$var integer 32 0 data_counter [31:0] $end
$upscope $end
$scope begin $ivl_for_loop0 $end
$var integer 32 1 i [31:0] $end
$upscope $end
$scope begin $ivl_for_loop1 $end
$var integer 32 2 i [31:0] $end
$upscope $end
$upscope $end
$enddefinitions $end
#0
$dumpvars
b0 2
b0 1
b0 0
bx /
b11010010110100101011010000001100101010010010000 .
x-
b100000001 ,
b11010010110100101011010000001100101010010010001 +
bx *
bx )
bx (
bx '
x&
0%
x$
bx #
bx "
x!
$end
#10000
0&
1%
#20000
0%
#30000
b0 /
b0 )
b0 "
b0 (
0!
1%
1&
#40000
0%
#50000
1%
0&
#60000
0%
#70000
1%
#80000
0%
#90000
1%
#100000
0%
#110000
1%
#120000
0%
#130000
1%
#140000
0%
#150000
b1 /
b101001011010010101101000000110010101001001000101 +
b1 "
b1 (
b1 0
1-
b10 *
1!
1%
b10 #
b10 '
1$
#160000
0%
#170000
b11 0
b1001 *
b100101101001010110100000011001010100100100010110 +
b10 "
b10 (
b1 )
1%
b1 #
b1 '
#180000
0%
#190000
0-
b10110100101011010000001100101010010010001011010 +
b10 )
1%
b0 #
b0 '
0$
#200000
0%
#210000
b11010010101101000000110010101001001000101101001 +
b1 "
b1 (
b11 )
1%
#220000
0%
#230000
b101001010110100000011001010100100100010110100101 +
b100 )
1%
#240000
0%
#250000
b100101011010000001100101010010010001011010010110 +
b10 "
b10 (
b101 )
1%
#260000
0%
#270000
b10101101000000110010101001001000101101001011010 +
b110 )
1%
#280000
0%
#290000
b10110100000011001010100100100010110100101101001 +
b1 "
b1 (
b111 )
1%
#300000
0%
#310000
b11010000001100101010010010001011010010110100101 +
b1000 )
1%
#320000
0%
#330000
b101000000110010101001001000101101001011010010101 +
b1001 )
1%
#340000
0%
#350000
b100000011001010100100100010110100101101001010110 +
b10 "
b10 (
b1010 )
1%
#360000
0%
#370000
b1100101010010010001011010010110100101011010 +
b1011 )
1%
#380000
0%
#390000
b110010101001001000101101001011010010101101000 +
b0 "
b0 (
b1100 )
1%
#400000
0%
#410000
b11001010100100100010110100101101001010110100000 +
b1101 )
1%
#420000
0%
#430000
b100101010010010001011010010110100101011010000001 +
b1 "
b1 (
b1110 )
1%
#440000
0%
#450000
b10101001001000101101001011010010101101000000110 +
b10 "
b10 (
b1111 )
1%
#460000
0%
#470000
b10100100100010110100101101001010110100000011001 +
b1 "
b1 (
b10000 )
1%
#480000
0%
#490000
b10010010001011010010110100101011010000001100101 +
b10001 )
1%
#500000
0%
#510000
b1001000101101001011010010101101000000110010101 +
b10010 )
1%
#520000
0%
#530000
b100100010110100101101001010110100000011001010100 +
b0 "
b0 (
b10011 )
1%
#540000
0%
#550000
b10001011010010110100101011010000001100101010010 +
b10 "
b10 (
b10100 )
1%
#560000
0%
#570000
b101101001011010010101101000000110010101001001 +
b1 "
b1 (
b10101 )
1%
#580000
0%
#590000
b10110100101101001010110100000011001010100100100 +
b0 "
b0 (
b10110 )
1%
#600000
0%
#610000
b11010010110100101011010000001100101010010010001 +
b1 "
b1 (
b10111 )
1%
#620000
0%
#630000
b101001011010010101101000000110010101001001000001 .
b11000 )
1%
#640000
0%
#650000
b100101101001010110100000011001010100100100000110 .
b10 "
b10 (
b11001 )
1%
#660000
0%
#670000
b10110100101011010000001100101010010010000011010 .
b11010 )
1%
#680000
0%
#690000
b11010010101101000000110010101001001000001101001 .
b1 "
b1 (
b11011 )
1%
#700000
0%
#710000
b101001010110100000011001010100100100000110100101 .
b11100 )
1%
#720000
0%
#730000
b100101011010000001100101010010010000011010010110 .
b10 "
b10 (
b11101 )
1%
#740000
0%
#750000
b10101101000000110010101001001000001101001011010 .
b11110 )
1%
#760000
0%
#770000
b10110100000011001010100100100000110100101101001 .
b1 "
b1 (
b11111 )
1%
#780000
0%
#790000
b11010000001100101010010010000011010010110100101 .
b100000 )
1%
#800000
0%
#810000
b101000000110010101001001000001101001011010010101 .
b100001 )
1%
#820000
0%
#830000
b100000011001010100100100000110100101101001010110 .
b10 "
b10 (
b100010 )
1%
#840000
0%
#850000
b1100101010010010000011010010110100101011010 .
b100011 )
1%
#860000
0%
#870000
b110010101001001000001101001011010010101101000 .
b0 "
b0 (
b100100 )
1%
#880000
0%
#890000
b11001010100100100000110100101101001010110100000 .
b100101 )
1%
#900000
0%
#910000
b100101010010010000011010010110100101011010000001 .
b1 "
b1 (
b100110 )
1%
#920000
0%
#930000
b10101001001000001101001011010010101101000000110 .
b10 "
b10 (
b100111 )
1%
#940000
0%
#950000
b10100100100000110100101101001010110100000011001 .
b1 "
b1 (
b101000 )
1%
#960000
0%
#970000
b10010010000011010010110100101011010000001100101 .
b101001 )
1%
#980000
0%
#990000
b1001000001101001011010010101101000000110010101 .
b101010 )
1%
#1000000
0%
#1010000
b100100000110100101101001010110100000011001010100 .
b0 "
b0 (
b101011 )
1%
#1020000
0%
#1030000
b10000011010010110100101011010000001100101010010 .
b10 "
b10 (
b101100 )
1%
#1040000
0%
#1050000
b1101001011010010101101000000110010101001001 .
b1 "
b1 (
b101101 )
1%
#1060000
0%
#1070000
b110100101101001010110100000011001010100100100 .
b0 "
b0 (
b101110 )
1%
#1080000
0%
#1090000
b11010010110100101011010000001100101010010010000 .
b101111 )
1%
#1100000
0%
#1110000
b10000000100 ,
b110000 )
1%
#1120000
0%
#1130000
b1000000010000 ,
b110001 )
1%
#1140000
0%
#1150000
b100000001000000 ,
b110010 )
1%
#1160000
0%
#1170000
b100000001 ,
b1 "
b1 (
b110011 )
1%
#1180000
0%
#1190000
b10000000100 ,
b0 "
b0 (
b110100 )
1%
#1200000
0%
#1210000
b1000000010000 ,
b110101 )
1%
#1220000
0%
#1230000
b100000001000000 ,
b110110 )
1%
#1240000
0%
#1250000
b100000001 ,
b1 "
b1 (
b110111 )
1%
#1260000
0%
#1270000
b11 /
b1 0
b10 "
b10 (
b111000 )
1%
#1280000
0%
#1290000
b11111111111111111111111111111111 0
b1 "
b1 (
1%
#1300000
0%
#1310000
b0 /
b0 )
b0 0
0!
1%
